redex/__init__.py
redex/function.py
redex/py.typed
redex/stack.py
redex/util.py
redex/version.py
redex/combinator/__init__.py
redex/combinator/_base.py
redex/combinator/_branch.py
redex/combinator/_drop.py
redex/combinator/_dup.py
redex/combinator/_fold.py
redex/combinator/_identity.py
redex/combinator/_parallel.py
redex/combinator/_residual.py
redex/combinator/_select.py
redex/combinator/_serial.py
redex-0.1.1.dist-info/LICENSE
redex-0.1.1.dist-info/METADATA
redex-0.1.1.dist-info/WHEEL
redex-0.1.1.dist-info/top_level.txt
redex-0.1.1.dist-info/RECORD
