Metadata-Version: 2.1
Name: redex
Version: 0.1.1
Summary: A combinator library for designing algorithms
Home-page: https://github.com/manifest/redex
Author: Andrei Nesterov
Author-email: ae.nesterov@gmail.com
License: UNKNOWN
Project-URL: Documentation, https://redex.readthedocs.io
Project-URL: Source Code, https://github.com/manifest/redex
Platform: UNKNOWN
Classifier: Development Status :: 3 - Alpha
Classifier: Intended Audience :: Developers
Classifier: Intended Audience :: Science/Research
Classifier: License :: OSI Approved :: Apache Software License
Classifier: Operating System :: OS Independent
Classifier: Programming Language :: Python :: 3.9
Classifier: Topic :: Scientific/Engineering
Classifier: Typing :: Typed
Requires-Python: >=3.9
License-File: LICENSE
Provides-Extra: development
Requires-Dist: hypothesis ; extra == 'development'
Requires-Dist: pylint ; extra == 'development'
Provides-Extra: docs
Requires-Dist: sphinx ; extra == 'docs'
Requires-Dist: furo ; extra == 'docs'
Requires-Dist: nbsphinx ; extra == 'docs'
Requires-Dist: ipykernel ; extra == 'docs'
